NatanStanek/__init__.py
NatanStanek-0.14.2.dist-info/METADATA
NatanStanek-0.14.2.dist-info/WHEEL
NatanStanek-0.14.2.dist-info/top_level.txt
NatanStanek-0.14.2.dist-info/RECORD
