Metadata-Version: 2.1
Name: NatanStanek
Version: 0.14.2
Summary: The real Natan Stanek python package
Home-page: https://github.com/JacoBSmitH101/NatanStanek
Author: James Mortimer
Author-email: jamesmortimer@bournside.smells.uk
License: MIT
